geoanasolution/__init__.py
geoanasolution/_analytical_base.py
geoanasolution/single_injection_well_2D.py
geoanasolution/theis.py
geoanasolution/uniform_flow.py
geoanasolution-0.4.2.dist-info/LICENSE
geoanasolution-0.4.2.dist-info/METADATA
geoanasolution-0.4.2.dist-info/WHEEL
geoanasolution-0.4.2.dist-info/top_level.txt
geoanasolution-0.4.2.dist-info/RECORD
