Metadata-Version: 2.1
Name: geoanasolution
Version: 0.4.2
Summary: A analytical solution library about geothermal research.
Home-page: https://gitee.com/geo-tech/geo-ana-solution.git
Author: Peng Hong
Author-email: minho_hong@foxmail.com
Requires-Python: >=3.6
License-File: LICENSE
